{
  "project_info": {
    "project_number": "266415714989",
    "firebase_url": "https://cloud-marks-android.firebaseio.com",
    "project_id": "cloud-marks-android",
    "storage_bucket": "cloud-marks-android.appspot.com"
  },
  "client": [
    {
      "client_info": {
        "mobilesdk_app_id": "1:266415714989:android:298e0bbd7ad3b43a",
        "android_client_info": {
          "package_name": "to.sava.cloudmarksandroid"
        }
      },
      "oauth_client": [
        {
          "client_id": "266415714989-q3d4hrove1vglk6c8aiq89uf2nfunvi9.apps.googleusercontent.com",
          "client_type": 3
        },
        {
          "client_id": "266415714989-q3v3vbukkj51l0iacp1ruda9fkqlckl2.apps.googleusercontent.com",
          "client_type": 1,
          "android_info": {
            "package_name": "to.sava.cloudmarksandroid",
            "certificate_hash": "cc5d19f9060d6cb0281a3fd3071c7990153d467b"
          }
        },
        {
          "client_id": "266415714989-q3d4hrove1vglk6c8aiq89uf2nfunvi9.apps.googleusercontent.com",
          "client_type": 3
        }
      ],
      "api_key": [
        {
          "current_key": "AIzaSyDvjWYHpP4KJgZ7Mu4UjeQflClmKU_7uL0"
        }
      ],
      "services": {
        "analytics_service": {
          "status": 1
        },
        "appinvite_service": {
          "status": 2,
          "other_platform_oauth_client": [
            {
              "client_id": "266415714989-q3d4hrove1vglk6c8aiq89uf2nfunvi9.apps.googleusercontent.com",
              "client_type": 3
            }
          ]
        },
        "ads_service": {
          "status": 2
        }
      }
    }
  ],
  "configuration_version": "1"
}